{"cameraMode":{"drawMode":0,"name":"Shaded","section":"Shading Mode"},"sceneLighting":true,"audioPlay":false,"sceneViewState":{"m_AlwaysRefresh":false,"showFog":true,"showSkybox":true,"showFlares":true,"showImageEffects":true,"showParticleSystems":true,"showVisualEffectGraphs":true,"m_FxEnabled":true},"in2DMode":false,"pivot":{"x":-0.2477077841758728,"y":0.8445985913276672,"z":0.14596357941627503},"rotation":{"x":-0.08061093091964722,"y":-0.0167474877089262,"z":0.0013546764384955168,"w":-0.9966057538986206},"size":3.6153786182403566,"orthographic":false}